{"timestamp": "2021-07-15 11:37:10", "sensors": [{"sensor_id": "sensor2", "value": -2.346555450584294}, {"sensor_id": "sensor5", "value": -54.6775303250114}, {"sensor_id": "sensor7", "value": 4.472422195222363}, {"sensor_id": "sensor8", "value": -4.798935319350143}, {"sensor_id": "sensor10", "value": -3.352158561049633}, {"sensor_id": "sensor12", "value": -61.98124992040181}, {"sensor_id": "sensor14", "value": -90.95405453521953}, {"sensor_id": "sensor15", "value": -8.80976021202926}, {"sensor_id": "sensor18", "value": 0.01534425041038389}, {"sensor_id": "sensor20", "value": -0.38781149755986505}, {"sensor_id": "sensor23", "value": 33.21035624242115}, {"sensor_id": "sensor24", "value": 0.1907423736828367}]}