{"timestamp": "2021-07-15 11:52:57", "sensors": [{"sensor_id": "sensor2", "value": -0.8600377319289023}, {"sensor_id": "sensor5", "value": -53.56982241575024}, {"sensor_id": "sensor6", "value": -4.66277532982727}, {"sensor_id": "sensor8", "value": -4.7978251131310605}, {"sensor_id": "sensor12", "value": -62.27766575308625}, {"sensor_id": "sensor15", "value": -4.3567283390665725}, {"sensor_id": "sensor18", "value": 0.01477998458166337}, {"sensor_id": "sensor19", "value": -7.411222754468852}, {"sensor_id": "sensor24", "value": 0.1755183303353472}]}