{"timestamp": "2021-07-15 15:38:17", "sensors": [{"sensor_id": "sensor0", "value": -0.020888305158358093}, {"sensor_id": "sensor1", "value": 9.92728107809628}, {"sensor_id": "sensor5", "value": -54.27827338574031}, {"sensor_id": "sensor8", "value": -4.798904640273676}, {"sensor_id": "sensor9", "value": 2.527277142940422}, {"sensor_id": "sensor10", "value": -3.3177483194310686}, {"sensor_id": "sensor12", "value": -61.83839954827246}, {"sensor_id": "sensor13", "value": 0.44349816055803093}, {"sensor_id": "sensor15", "value": 6.243915183673857}, {"sensor_id": "sensor16", "value": -3.6507991863772484}, {"sensor_id": "sensor18", "value": 0.029219302773360233}, {"sensor_id": "sensor19", "value": 6.658561262326504}, {"sensor_id": "sensor20", "value": -1.0367034534159711}, {"sensor_id": "sensor23", "value": 34.41724945101274}]}