{"timestamp": "2021-07-15 19:35:18", "sensors": [{"sensor_id": "sensor1", "value": 10.038974563403404}, {"sensor_id": "sensor5", "value": -53.94290526211925}, {"sensor_id": "sensor8", "value": -4.809161491451114}, {"sensor_id": "sensor9", "value": 4.99651793458122}, {"sensor_id": "sensor12", "value": -62.28664379370851}, {"sensor_id": "sensor14", "value": -91.0616072275821}, {"sensor_id": "sensor15", "value": -0.528391372853846}, {"sensor_id": "sensor19", "value": 2.122649904390649}, {"sensor_id": "sensor20", "value": 0.3472262740177536}, {"sensor_id": "sensor22", "value": 6.581113890868705}, {"sensor_id": "sensor23", "value": 33.02387975463717}, {"sensor_id": "sensor24", "value": 0.7419940290266334}]}