{"timestamp": "2021-07-15 17:03:46", "sensors": [{"sensor_id": "sensor2", "value": -1.794702374934616}, {"sensor_id": "sensor3", "value": -6.750565537551833}, {"sensor_id": "sensor5", "value": -53.0364720984415}, {"sensor_id": "sensor8", "value": -4.795838114208008}, {"sensor_id": "sensor10", "value": -3.399906449499301}, {"sensor_id": "sensor12", "value": -61.229239199142995}, {"sensor_id": "sensor15", "value": -0.08648571248064296}, {"sensor_id": "sensor18", "value": 0.013596213272827827}, {"sensor_id": "sensor19", "value": -4.481366086196758}, {"sensor_id": "sensor22", "value": -1.9561627602749556}, {"sensor_id": "sensor23", "value": 34.211182610728144}, {"sensor_id": "sensor24", "value": 0.5704937152653693}]}